phone_email_verifier/ProcessException.py
phone_email_verifier/__init__.py
phone_email_verifier/contacts_verifier.py
phone_email_verifier/email_verifier.py
phone_email_verifier/function.py
phone_email_verifier/phone_verifier.py
phone_email_verifier/treatment.py
phone_email_verifier/treatment_email.py
phone_email_verifier/treatment_phone.py
phone_email_verifier-0.0.4.dist-info/LICENSE
phone_email_verifier-0.0.4.dist-info/METADATA
phone_email_verifier-0.0.4.dist-info/WHEEL
phone_email_verifier-0.0.4.dist-info/top_level.txt
phone_email_verifier-0.0.4.dist-info/RECORD
