Metadata-Version: 2.1
Name: phone-email-verifier
Version: 0.0.4
Summary: Validation of the email or international or local telephone number
Home-page: https://github.com/Bogro/phone_email_verifier
Author: Christian BOGRO
Author-email: bogrolcr@gmail.com
License: MIT
Download-URL: https://github.com/Bogro/phone_email_verifier/tarball/master
Keywords: email,phone number,filter,blocking,text,phone local,phone international
Platform: UNKNOWN
